ensure_file/__init__.py
ensure_file-1.1.2.dist-info/LICENSE
ensure_file-1.1.2.dist-info/METADATA
ensure_file-1.1.2.dist-info/WHEEL
ensure_file-1.1.2.dist-info/top_level.txt
ensure_file-1.1.2.dist-info/RECORD
