Metadata-Version: 2.1
Name: ensure_file
Version: 1.1.2
Summary: An easy way to manage file creation.
Author-email: Hazel <trinkey@duck.com>
Project-URL: Homepage, https://github.com/trinkey/ensure-file
Project-URL: Issues, https://github.com/trinkey/ensure-file/issues
Classifier: Programming Language :: Python :: 3
Classifier: License :: OSI Approved :: GNU Affero General Public License v3
Classifier: Operating System :: OS Independent
Requires-Python: >=3.6
License-File: LICENSE
